[{"score": 2.089377, "link": "http://dbpedia.org/resource/Foreign_exchange_market"}, 
{"score": 1.788507, "link": "http://dbpedia.org/resource/Derivative_%28finance%29"}, 
{"score": 1.752274, "link": "http://dbpedia.org/resource/Goldman_Sachs"}, 
{"score": 1.716835, "link": "http://dbpedia.org/resource/Stock_exchange"}, 
{"score": 1.715530, "link": "http://dbpedia.org/resource/Bond_%28finance%29"}, 
{"score": 1.657008, "link": "http://dbpedia.org/resource/Financial_services"}, 
{"score": 1.608098, "link": "http://dbpedia.org/resource/Stock_market"}, 
{"score": 1.541937, "link": "http://dbpedia.org/resource/Financial_regulation"}, 
{"score": 1.528942, "link": "http://dbpedia.org/resource/Bank_of_America"}, 
{"score": 1.477250, "link": "http://dbpedia.org/resource/Holding_company"}, 
{"score": 1.462136, "link": "http://dbpedia.org/resource/Troubled_Asset_Relief_Program"}, 
{"score": 1.457628, "link": "http://dbpedia.org/resource/Interest_rate"}, 
{"score": 1.451373, "link": "http://dbpedia.org/resource/Marketing"}, 
{"score": 1.311705, "link": "http://dbpedia.org/resource/Private_bank"}, 
{"score": 1.225925, "link": "http://dbpedia.org/resource/Valuation_%28finance%29"}, 
{"score": 1.163312, "link": "http://dbpedia.org/resource/Brand"}, 
{"score": 1.156519, "link": "http://dbpedia.org/resource/Market_research"}, 
{"score": 1.137564, "link": "http://dbpedia.org/resource/Trade"}, 
{"score": 1.107019, "link": "http://dbpedia.org/resource/Microsoft"}, 
{"score": 1.089959, "link": "http://dbpedia.org/resource/Conglomerate_%28company%29"}, 
{"score": 1.066533, "link": "http://dbpedia.org/resource/Standard_&_Poor%27s"}, 
{"score": 1.062988, "link": "http://dbpedia.org/resource/EBay"}, 
{"score": 1.058422, "link": "http://dbpedia.org/resource/Bankruptcy"}, 
{"score": 1.051363, "link": "http://dbpedia.org/resource/Monopoly"}, 
{"score": 1.035096, "link": "http://dbpedia.org/resource/Business"}, 
{"score": 0.993750, "link": "http://dbpedia.org/resource/Business_cycle"}, 
{"score": 0.978672, "link": "http://dbpedia.org/resource/Google"}, 
{"score": 0.932500, "link": "http://dbpedia.org/resource/Apple_Inc."}, 
{"score": 0.926502, "link": "http://dbpedia.org/resource/Advertising"}, 
{"score": 0.918157, "link": "http://dbpedia.org/resource/IBM"}, 
{"score": 0.913738, "link": "http://dbpedia.org/resource/Construction"}, 
{"score": 0.892554, "link": "http://dbpedia.org/resource/Information_technology"}, 
{"score": 0.892065, "link": "http://dbpedia.org/resource/Risk"}, 
{"score": 0.890629, "link": "http://dbpedia.org/resource/Hong_Kong"}, 
{"score": 0.886384, "link": "http://dbpedia.org/resource/Lobbying"}, 
{"score": 0.866450, "link": "http://dbpedia.org/resource/Public_relations"}, 
{"score": 0.864182, "link": "http://dbpedia.org/resource/Flea_market"}, 
{"score": 0.860727, "link": "http://dbpedia.org/resource/Steve_Jobs"}, 
{"score": 0.853102, "link": "http://dbpedia.org/resource/Life_insurance"}, 
{"score": 0.852248, "link": "http://dbpedia.org/resource/Street"}, 
{"score": 0.826310, "link": "http://dbpedia.org/resource/Organic_food"}, 
{"score": 0.825329, "link": "http://dbpedia.org/resource/East_River"}, 
{"score": 0.823932, "link": "http://dbpedia.org/resource/Filling_station"}, 
{"score": 0.810534, "link": "http://dbpedia.org/resource/Fashion"}, 
{"score": 0.810265, "link": "http://dbpedia.org/resource/Renewable_energy"}, 
{"score": 0.808795, "link": "http://dbpedia.org/resource/Detroit"}, 
{"score": 0.803915, "link": "http://dbpedia.org/resource/Unemployment"}, 
{"score": 0.798175, "link": "http://dbpedia.org/resource/Boeing"}, 
{"score": 0.780237, "link": "http://dbpedia.org/resource/Hotel"}, 
{"score": 0.777290, "link": "http://dbpedia.org/resource/Shopping_mall"}, 
{"score": 0.763247, "link": "http://dbpedia.org/resource/The_New_York_Times"}, 
{"score": 0.740855, "link": "http://dbpedia.org/resource/Car_rental"}, 
{"score": 0.737809, "link": "http://dbpedia.org/resource/Property"}, 
{"score": 0.737312, "link": "http://dbpedia.org/resource/Masonry"}, 
{"score": 0.736078, "link": "http://dbpedia.org/resource/Mass_media"}, 
{"score": 0.731939, "link": "http://dbpedia.org/resource/Clothing"}, 
{"score": 0.731832, "link": "http://dbpedia.org/resource/Biotechnology"}, 
{"score": 0.731274, "link": "http://dbpedia.org/resource/DuPont"}, 
{"score": 0.728274, "link": "http://dbpedia.org/resource/Tourism"}, 
{"score": 0.698266, "link": "http://dbpedia.org/resource/Lawsuit"}, 
{"score": 0.696789, "link": "http://dbpedia.org/resource/Steel"}, 
{"score": 0.693748, "link": "http://dbpedia.org/resource/Government"}, 
{"score": 0.683940, "link": "http://dbpedia.org/resource/Prohibition"}, 
{"score": 0.674649, "link": "http://dbpedia.org/resource/September_11_attacks"}, 
{"score": 0.673273, "link": "http://dbpedia.org/resource/Gold"}, 
{"score": 0.663883, "link": "http://dbpedia.org/resource/Windows_XP"}, 
{"score": 0.660893, "link": "http://dbpedia.org/resource/Electric_power_transmission"}, 
{"score": 0.657487, "link": "http://dbpedia.org/resource/Education"}, 
{"score": 0.647849, "link": "http://dbpedia.org/resource/Environmentalism"}, 
{"score": 0.640515, "link": "http://dbpedia.org/resource/Transparency_%28behavior%29"}, 
{"score": 0.640474, "link": "http://dbpedia.org/resource/Honda"}, 
{"score": 0.634142, "link": "http://dbpedia.org/resource/Coal"}, 
{"score": 0.633086, "link": "http://dbpedia.org/resource/Rapid_transit"}, 
{"score": 0.623976, "link": "http://dbpedia.org/resource/Rationing"}]
